output_shape/__init__.py
output_shape-0.0.1.dist-info/LICENSE
output_shape-0.0.1.dist-info/METADATA
output_shape-0.0.1.dist-info/WHEEL
output_shape-0.0.1.dist-info/top_level.txt
output_shape-0.0.1.dist-info/RECORD
