Metadata-Version: 2.1
Name: output-shape
Version: 0.0.1
Summary: A very lightweight and minimalistic output shape examiner of layers and models.
Home-page: https://github.com/avocardio/output-shape
Author: avocardio
License: MIT
Platform: UNKNOWN
Classifier: Development Status :: 4 - Beta
Classifier: Intended Audience :: Developers
Classifier: Topic :: Scientific/Engineering :: Artificial Intelligence
Classifier: License :: OSI Approved :: MIT License
Classifier: Programming Language :: Python :: 3.6
License-File: LICENSE
Requires-Dist: torch (>=1.6)
